ostium_python_sdk/__init__.py
ostium_python_sdk/balance.py
ostium_python_sdk/config.py
ostium_python_sdk/constants.py
ostium_python_sdk/exceptions.py
ostium_python_sdk/faucet.py
ostium_python_sdk/formulae.py
ostium_python_sdk/formulae_wrapper.py
ostium_python_sdk/ostium.py
ostium_python_sdk/price.py
ostium_python_sdk/sdk.py
ostium_python_sdk/subgraph.py
ostium_python_sdk/utils.py
ostium_python_sdk/abi/__init__.py
ostium_python_sdk/abi/faucet_testnet_abi.py
ostium_python_sdk/abi/pairs_info_abi.py
ostium_python_sdk/abi/pairs_storage_abi.py
ostium_python_sdk/abi/trading_abi.py
ostium_python_sdk/abi/trading_storage_abi.py
ostium_python_sdk/abi/usdc_abi.py
ostium_python_sdk/abi/vault_abi.py
ostium_python_sdk/scscript/__init__.py
ostium_python_sdk/scscript/funding.py
ostium_python_sdk/scscript/pairinfos.py
tests/__init__.py
tests/conftest.py
tests/disabled_test_builder_fee.py
tests/disabled_test_close_trade.py
tests/disabled_test_funding.py
tests/disabled_test_slippage.py
tests/test_current_total_profit_p.py
tests/test_current_total_profit_raw.py
tests/test_current_trade_profit_p.py
tests/test_current_trade_profit_raw.py
tests/test_get_opening_fee.py
tests/test_get_pending_acc_funding_fees.py
tests/test_get_price_impact.py
tests/test_get_trade_funding_fee.py
tests/test_get_trade_rollover_fee.py
tests/test_get_trade_value.py
tests/test_max_leverage.py
tests/test_overnight_max_leverage.py
tests/test_remove_collateral_from_leverage.py
tests/test_remove_collateral_with_collateral.py
tests/test_target_funding_rate.py
tests/test_top_up_with_collateral.py
tests/test_top_up_with_leverage.py
tests/test_trade_get_sl_price.py
tests/test_trade_get_tp_price.py
tests/test_trade_liquidation_price.py
ostium_python_sdk-3.0.1.dist-info/METADATA
ostium_python_sdk-3.0.1.dist-info/WHEEL
ostium_python_sdk-3.0.1.dist-info/top_level.txt
ostium_python_sdk-3.0.1.dist-info/RECORD
