Metadata-Version: 2.4
Name: ostium-python-sdk
Version: 3.0.1
Summary: A python based SDK developed for interacting with Ostium, a leveraged trading application for trading currencies, commodities, indices, crypto and more.
Home-page: https://github.com/0xOstium/ostium-python-sdk
Author: ami@ostium.io
Classifier: Development Status :: 3 - Alpha
Classifier: Intended Audience :: Developers
Classifier: License :: OSI Approved :: MIT License
Classifier: Programming Language :: Python :: 3
Classifier: Programming Language :: Python :: 3.8
Requires-Python: >=3.8
Requires-Dist: web3>=6.0.0
Requires-Dist: gql==3.5.0
Requires-Dist: graphql-core==3.2.5
Requires-Dist: pytest
Requires-Dist: pytest-cov
Requires-Dist: pytest-asyncio
Requires-Dist: humanize
Requires-Dist: aiohttp>=3.8.0
Requires-Dist: requests>=2.28.0
Requires-Dist: python-dotenv>=0.19.0
Requires-Dist: pydantic>=2.0.0
Requires-Dist: asyncio>=3.4.3
Provides-Extra: dev
Requires-Dist: pytest; extra == "dev"
Requires-Dist: pytest-cov; extra == "dev"
Requires-Dist: pytest-asyncio; extra == "dev"
Dynamic: author
Dynamic: classifier
Dynamic: description
Dynamic: description-content-type
Dynamic: home-page
Dynamic: provides-extra
Dynamic: requires-dist
Dynamic: requires-python
Dynamic: summary
